{
  "location_id": "662190",
  "name": "Coral Sea Holiday Resort & Aqua Park",
  "description": "Offering the unsurpassed panoramic views of the Red Sea, Coral Sea Holiday Village Resort presents a comprehensive under-one-roof concept that meets the need of every discerning leisure traveler. This 5-star resort houses: 484 elegant guest rooms with modern amenities, superbly-designed facilities and 13 exciting dining and lifestyle choices for a multi-dimensional experience. It is our privilege to enchant our guests with courteous and attentive service that is the hallmark of Coral Sea Holiday Village Resort; we deliver only the best!",
  "web_url": "https://www.tripadvisor.com/Hotel_Review-g297555-d662190-Reviews-Coral_Sea_Holiday_Resort_Aqua_Park-Sharm_El_Sheikh_South_Sinai_Red_Sea_and_Sinai.html?m=66827",
  "address_obj": {
    "street1": "Elsalam Road",
    "street2": "Nabq Bay",
    "city": "Sharm El Sheikh",
    "country": "Egypt",
    "postalcode": "46628",
    "address_string": "Elsalam Road Nabq Bay, Sharm El Sheikh 46628 Egypt"
  },
  "ancestors": [
    {
      "level": "Municipality",
      "name": "Sharm El Sheikh",
      "location_id": "297555"
    },
    {
      "level": "District",
      "name": "South Sinai",
      "location_id": "297556"
    },
    {
      "level": "Region",
      "name": "Red Sea and Sinai",
      "location_id": "297545"
    },
    {
      "level": "Country",
      "name": "Egypt",
      "location_id": "294200"
    }
  ],
  "latitude": "28.03999",
  "longitude": "34.429966",
  "timezone": "Africa/Cairo",
  "write_review": "https://www.tripadvisor.com/UserReview-g297555-d662190-Coral_Sea_Holiday_Resort_Aqua_Park-Sharm_El_Sheikh_South_Sinai_Red_Sea_and_Sinai.html?m=66827",
  "ranking_data": {
    "geo_location_id": "297555",
    "ranking_string": "#53 of 279 hotels in Sharm El Sheikh",
    "geo_location_name": "Sharm El Sheikh",
    "ranking_out_of": "279",
    "ranking": "53"
  },
  "rating": "4.5",
  "rating_image_url": "https://www.tripadvisor.com/img/cdsi/img2/ratings/traveler/4.5-66827-5.svg",
  "num_reviews": "8746",
  "review_rating_count": {
    "1": "167",
    "2": "245",
    "3": "628",
    "4": "1830",
    "5": "5876"
  },
  "subratings": {
    "0": {
      "name": "rate_location",
      "localized_name": "Location",
      "rating_image_url": "https://static.tacdn.com/img2/ratings/traveler/ss4.5.svg",
      "value": "4.5"
    },
    "1": {
      "name": "rate_sleep",
      "localized_name": "Sleep Quality",
      "rating_image_url": "https://static.tacdn.com/img2/ratings/traveler/ss4.5.svg",
      "value": "4.5"
    },
    "2": {
      "name": "rate_room",
      "localized_name": "Rooms",
      "rating_image_url": "https://static.tacdn.com/img2/ratings/traveler/ss4.5.svg",
      "value": "4.5"
    },
    "3": {
      "name": "rate_service",
      "localized_name": "Service",
      "rating_image_url": "https://static.tacdn.com/img2/ratings/traveler/ss4.5.svg",
      "value": "4.5"
    },
    "4": {
      "name": "rate_value",
      "localized_name": "Value",
      "rating_image_url": "https://static.tacdn.com/img2/ratings/traveler/ss4.5.svg",
      "value": "4.5"
    },
    "5": {
      "name": "rate_cleanliness",
      "localized_name": "Cleanliness",
      "rating_image_url": "https://static.tacdn.com/img2/ratings/traveler/ss4.5.svg",
      "value": "4.5"
    }
  },
  "photo_count": "9096",
  "see_all_photos": "https://www.tripadvisor.com/Hotel_Review-g297555-d662190-m66827-Reviews-Coral_Sea_Holiday_Resort_Aqua_Park-Sharm_El_Sheikh_South_Sinai_Red_Sea_and_Sinai.html#photos",
  "price_level": "$$",
  "amenities": [
    "Internet",
    "Beachfront",
    "Suites",
    "Paid Internet",
    "Beach Access",
    "Pool",
    "Kids Activities",
    "Room service",
    "Free parking",
    "Wheelchair access",
    "Restaurant",
    "Bar/Lounge",
    "Pets Allowed",
    "Spa",
    "Airport transportation",
    "Wifi",
    "Public Wifi",
    "Dry Cleaning",
    "Meeting rooms",
    "Tennis Court",
    "Business center",
    "Fitness center",
    "Laundry Service",
    "Concierge",
    "Banquet Room",
    "Air conditioning",
    "Family Rooms",
    "Multilingual Staff",
    "Smoking rooms available",
    "Accessible rooms",
    "Minibar",
    "Conference Facilities",
    "Babysitting",
    "Safe",
    "Rooftop Bar",
    "Swimup Bar",
    "Heated pool",
    "Rooftop Terrace",
    "Breakfast Buffet",
    "Poolside Bar",
    "Private Balcony",
    "Outdoor pool",
    "Private Beaches",
    "Private Pools",
    "Breakfast Available",
    "Parking",
    "Free airport transportation",
    "Facilities for Disabled Guests",
    "Housekeeping",
    "Kids Club",
    "Sauna",
    "Aerobics",
    "Arabic",
    "Convenience Store",
    "Currency Exchange",
    "Darts",
    "Diving",
    "Entertainment Staff",
    "Evening Entertainment",
    "Facial Treatments",
    "Fitness Classes",
    "Fitness / Spa Locker Rooms",
    "24-Hour Front Desk",
    "Gift Shop",
    "Hammam",
    "Indoor Play Area for Children",
    "Interconnected room(s) available",
    "Ironing Service",
    "Italian",
    "Kid-Friendly Buffet",
    "Kids' Outdoor Play Equipment",
    "Massage",
    "Pool / Beach Towels",
    "Russian",
    "Salon",
    "24-Hour Security",
    "Shops",
    "Sun Loungers / Beach Chairs",
    "Sun Umbrellas",
    "Table Tennis",
    "Taxi Service",
    "Flatscreen TV"
  ],
  "category": {
    "name": "hotel",
    "localized_name": "Hotel"
  },
  "subcategory": [
    {
      "name": "hotel",
      "localized_name": "Hotel"
    }
  ],
  "styles": [
    "Park View",
    "Hidden Gem"
  ],
  "neighborhood_info": [],
  "trip_types": [
    {
      "name": "business",
      "localized_name": "Business",
      "value": "21"
    },
    {
      "name": "couples",
      "localized_name": "Couples",
      "value": "2255"
    },
    {
      "name": "solo",
      "localized_name": "Solo travel",
      "value": "55"
    },
    {
      "name": "family",
      "localized_name": "Family",
      "value": "4670"
    },
    {
      "name": "friends",
      "localized_name": "Friends getaway",
      "value": "662"
    }
  ],
  "awards": [
    {
      "award_type": "Travelers Choice",
      "year": "2023",
      "images": {
        "tiny": "https://static.tacdn.com/img2/travelers_choice/widgets/tchotel_2023_L.png",
        "small": "https://static.tacdn.com/img2/travelers_choice/widgets/tchotel_2023_L.png",
        "large": "https://static.tacdn.com/img2/travelers_choice/widgets/tchotel_2023_L.png"
      },
      "categories": [],
      "display_name": "Travelers Choice"
    }
  ]
}