{
  "data": [
    {
      "id": 945941029,
      "lang": "en",
      "location_id": 23631662,
      "published_date": "2024-04-09T07:13:02Z",
      "rating": 5,
      "helpful_votes": 0,
      "rating_image_url": "https://www.tripadvisor.com/img/cdsi/img2/ratings/traveler/s5.0-66827-5.svg",
      "url": "https://www.tripadvisor.com/ShowUserReviews-g295424-d23631662-r945941029-Reviews-The_First_Collection_at_Jumeirah_Village_Circle-Dubai_Emirate_of_Dubai.html?m=66827#review945941029",
      "text": "The team at The First were amazing. From the receptionist to the Management at the diner were incredible. Cris and Azurk (I think I spelled her name wrong) were very accommodating and from day one made sure I felt welcomed and maximized my experience.  My go to place whenever I am in Dubai.",
      "title": "Anniversary Trip 2024",
      "trip_type": "Family",
      "travel_date": "2024-02-29",
      "user": {
        "username": "Sunshine18296824537",
        "user_location": {
          "id": "null"
        },
        "avatar": {
          "thumbnail": "https://media-cdn.tripadvisor.com/media/photo-t/1a/f6/f1/b8/default-avatar-2020-22.jpg",
          "small": "https://media-cdn.tripadvisor.com/media/photo-l/1a/f6/f1/b8/default-avatar-2020-22.jpg",
          "medium": "https://media-cdn.tripadvisor.com/media/photo-f/1a/f6/f1/b8/default-avatar-2020-22.jpg",
          "large": "https://media-cdn.tripadvisor.com/media/photo-p/1a/f6/f1/b8/default-avatar-2020-22.jpg",
          "original": "https://media-cdn.tripadvisor.com/media/photo-o/1a/f6/f1/b8/default-avatar-2020-22.jpg"
        }
      },
      "subratings": {}
    },
    {
      "id": 945889681,
      "lang": "en",
      "location_id": 23631662,
      "published_date": "2024-04-08T18:00:00Z",
      "rating": 5,
      "helpful_votes": 0,
      "rating_image_url": "https://www.tripadvisor.com/img/cdsi/img2/ratings/traveler/s5.0-66827-5.svg",
      "url": "https://www.tripadvisor.com/ShowUserReviews-g295424-d23631662-r945889681-Reviews-The_First_Collection_at_Jumeirah_Village_Circle-Dubai_Emirate_of_Dubai.html?m=66827#review945889681",
      "text": "The hotel is very very beautiful, very very clean! the breakfast is good and plentiful! the swimming pool is large, clean and very pretty with a large screen! The staff is very kind ! I asked for a room with a bathtub and a view from very high up, they responded to my request, I give it 10/10! Really only positive! I will come back!! Little extra: I thank Rubel for helping me with my suitcases!",
      "title": "Very good hotel !!!!",
      "trip_type": "Solo travel",
      "travel_date": "2024-03-31",
      "user": {
        "username": "mikaelam821",
        "user_location": {
          "id": "null"
        },
        "avatar": {
          "thumbnail": "https://media-cdn.tripadvisor.com/media/photo-t/1a/f6/f1/42/default-avatar-2020-20.jpg",
          "small": "https://media-cdn.tripadvisor.com/media/photo-l/1a/f6/f1/42/default-avatar-2020-20.jpg",
          "medium": "https://media-cdn.tripadvisor.com/media/photo-f/1a/f6/f1/42/default-avatar-2020-20.jpg",
          "large": "https://media-cdn.tripadvisor.com/media/photo-p/1a/f6/f1/42/default-avatar-2020-20.jpg",
          "original": "https://media-cdn.tripadvisor.com/media/photo-o/1a/f6/f1/42/default-avatar-2020-20.jpg"
        }
      },
      "subratings": {
        "0": {
          "name": "RATE_VALUE",
          "rating_image_url": "https://www.tripadvisor.com/img/cdsi/img2/ratings/traveler/s5.0-66827-5.svg",
          "value": 5,
          "localized_name": "Value"
        },
        "1": {
          "name": "RATE_ROOM",
          "rating_image_url": "https://www.tripadvisor.com/img/cdsi/img2/ratings/traveler/s5.0-66827-5.svg",
          "value": 5,
          "localized_name": "Rooms"
        },
        "2": {
          "name": "RATE_LOCATION",
          "rating_image_url": "https://www.tripadvisor.com/img/cdsi/img2/ratings/traveler/s5.0-66827-5.svg",
          "value": 5,
          "localized_name": "Location"
        },
        "3": {
          "name": "RATE_CLEANLINESS",
          "rating_image_url": "https://www.tripadvisor.com/img/cdsi/img2/ratings/traveler/s5.0-66827-5.svg",
          "value": 5,
          "localized_name": "Cleanliness"
        },
        "4": {
          "name": "RATE_SERVICE",
          "rating_image_url": "https://www.tripadvisor.com/img/cdsi/img2/ratings/traveler/s5.0-66827-5.svg",
          "value": 5,
          "localized_name": "Service"
        },
        "5": {
          "name": "RATE_SLEEP",
          "rating_image_url": "https://www.tripadvisor.com/img/cdsi/img2/ratings/traveler/s5.0-66827-5.svg",
          "value": 5,
          "localized_name": "Sleep Quality"
        }
      }
    },
    {
      "id": 945783784,
      "lang": "en",
      "location_id": 23631662,
      "published_date": "2024-04-08T01:35:37Z",
      "rating": 4,
      "helpful_votes": 0,
      "rating_image_url": "https://www.tripadvisor.com/img/cdsi/img2/ratings/traveler/s4.0-66827-5.svg",
      "url": "https://www.tripadvisor.com/ShowUserReviews-g295424-d23631662-r945783784-Reviews-The_First_Collection_at_Jumeirah_Village_Circle-Dubai_Emirate_of_Dubai.html?m=66827#review945783784",
      "text": "The Hotel is Very nice over All! What i liked the most is the kind Lifeguards at the pool especially unni😄 i would love to get a little bit more diversiti at the restaurants because its the same everyday. All over all its a very nice hotel. We will come back",
      "title": "Amazing Lifeguard Unni😄",
      "trip_type": "Family",
      "travel_date": "2024-04-30",
      "user": {
        "username": "598mischas",
        "user_location": {
          "id": "null"
        },
        "avatar": {
          "thumbnail": "https://media-cdn.tripadvisor.com/media/photo-t/1a/f6/f3/23/default-avatar-2020-28.jpg",
          "small": "https://media-cdn.tripadvisor.com/media/photo-l/1a/f6/f3/23/default-avatar-2020-28.jpg",
          "medium": "https://media-cdn.tripadvisor.com/media/photo-f/1a/f6/f3/23/default-avatar-2020-28.jpg",
          "large": "https://media-cdn.tripadvisor.com/media/photo-p/1a/f6/f3/23/default-avatar-2020-28.jpg",
          "original": "https://media-cdn.tripadvisor.com/media/photo-o/1a/f6/f3/23/default-avatar-2020-28.jpg"
        }
      },
      "subratings": {
        "0": {
          "name": "RATE_VALUE",
          "rating_image_url": "https://www.tripadvisor.com/img/cdsi/img2/ratings/traveler/s5.0-66827-5.svg",
          "value": 5,
          "localized_name": "Value"
        },
        "1": {
          "name": "RATE_ROOM",
          "rating_image_url": "https://www.tripadvisor.com/img/cdsi/img2/ratings/traveler/s5.0-66827-5.svg",
          "value": 5,
          "localized_name": "Rooms"
        },
        "2": {
          "name": "RATE_LOCATION",
          "rating_image_url": "https://www.tripadvisor.com/img/cdsi/img2/ratings/traveler/s4.0-66827-5.svg",
          "value": 4,
          "localized_name": "Location"
        },
        "3": {
          "name": "RATE_CLEANLINESS",
          "rating_image_url": "https://www.tripadvisor.com/img/cdsi/img2/ratings/traveler/s5.0-66827-5.svg",
          "value": 5,
          "localized_name": "Cleanliness"
        },
        "4": {
          "name": "RATE_SERVICE",
          "rating_image_url": "https://www.tripadvisor.com/img/cdsi/img2/ratings/traveler/s5.0-66827-5.svg",
          "value": 5,
          "localized_name": "Service"
        },
        "5": {
          "name": "RATE_SLEEP",
          "rating_image_url": "https://www.tripadvisor.com/img/cdsi/img2/ratings/traveler/s5.0-66827-5.svg",
          "value": 5,
          "localized_name": "Sleep Quality"
        }
      }
    },
    {
      "id": 945689633,
      "lang": "en",
      "location_id": 23631662,
      "published_date": "2024-04-07T08:38:52Z",
      "rating": 5,
      "helpful_votes": 0,
      "rating_image_url": "https://www.tripadvisor.com/img/cdsi/img2/ratings/traveler/s5.0-66827-5.svg",
      "url": "https://www.tripadvisor.com/ShowUserReviews-g295424-d23631662-r945689633-Reviews-The_First_Collection_at_Jumeirah_Village_Circle-Dubai_Emirate_of_Dubai.html?m=66827#review945689633",
      "text": "When I was looking for a hotel online I searched for days and days to find what would be the best place to stay , based on value and location and quality of the hotel , I wasn’t sure what to expect from this hotel as the price seemed very cheap for the two weeks stay . \nI arrived at the hotel and first impressions were good , the room was big it was clean and it was new ! , you couldn’t fault anything , it even had modern light switch controls by the touch of a button . The walls were spotless looked as if nobody had ever stayed in my room .  Everything you could possibly need was in the room , including wardrobes and fridge and ironing board and coffee making facilities. \nThe location was a nice residential area , quiet and accessible by taxi to anywhere you need to be in 20 mins or so for a small fee . Personally the location was good for me as it felt like living in your own apartment rather than a hotel . \nThe hotel offers a selection of restaurants and bars and has a very pleasant swimming pool area, as well as other facilities too , they organised a lot of excursions for me from the concierge that were all very good value and enjoyable experiences. \nFor the entire duration of my stay the room was silent , and no noise from other guests , I’ve stayed in places which are 10 times the price that don’t have this level of comfort . \nThey even offer a free day pass to a beach club on the palm , and a free bus to get there ! . \nCompletely free ! \nThe value here is unbelievable, back in England you wouldn’t get anything at this price of around 65 pound per night , it’s so affordable and luxury too ! , my advice to anyone is to stay at this hotel and go enjoy Dubai . If you want a beach there is plenty in Dubai to go to . \nThis could be one of the best hotels in Dubai at the moment and it’s highly rated on here too . \nAmazing I’d definitely be returning to this amazing place .",
      "title": "Could this be the best hotel in Dubai ?",
      "trip_type": "Solo travel",
      "travel_date": "2024-03-31",
      "user": {
        "username": "dannyd649",
        "user_location": {
          "id": "186478",
          "name": "Newcastle, County Down, Northern Ireland"
        },
        "avatar": {
          "thumbnail": "https://media-cdn.tripadvisor.com/media/photo-t/1a/f6/de/0a/default-avatar-2020-35.jpg",
          "small": "https://media-cdn.tripadvisor.com/media/photo-l/1a/f6/de/0a/default-avatar-2020-35.jpg",
          "medium": "https://media-cdn.tripadvisor.com/media/photo-f/1a/f6/de/0a/default-avatar-2020-35.jpg",
          "large": "https://media-cdn.tripadvisor.com/media/photo-p/1a/f6/de/0a/default-avatar-2020-35.jpg",
          "original": "https://media-cdn.tripadvisor.com/media/photo-o/1a/f6/de/0a/default-avatar-2020-35.jpg"
        }
      },
      "subratings": {},
      "owner_response": {
        "id": 945880293,
        "title": "Owner response",
        "text": "dannyd649, we're blown away by your incredible review. \n\nWe are overjoyed to read your detailed feedback and to know that every aspect of your visit exceeded your expectations.\nIt brings us immense pleasure to learn that our facilities, including the modern and comfortable rooms resonated with your preferences during your time with us. \nYour acknowledgment of our efforts in maintaining a pristine environment and providing a serene atmosphere for relaxation means the world to us. We are continually striving to exceed our guests' expectations, and your words encourage us to persist in delivering exceptional hospitality. Your compliments towards our dedicated team members warm our hearts. Rest assured, we've conveyed your gratitude to them, and they are thrilled to have contributed to making your stay memorable.\n\nWe are honored to have earned your trust and we look forward to welcoming you back to our hotel in the near future.\n\nWarm Regards,\nGeorge Ghaly",
        "lang": "en",
        "author": "George Ghaly",
        "published_date": "2024-04-08T16:07:29Z"
      }
    },
    {
      "id": 945601429,
      "lang": "en",
      "location_id": 23631662,
      "published_date": "2024-04-06T14:36:42Z",
      "rating": 5,
      "helpful_votes": 0,
      "rating_image_url": "https://www.tripadvisor.com/img/cdsi/img2/ratings/traveler/s5.0-66827-5.svg",
      "url": "https://www.tripadvisor.com/ShowUserReviews-g295424-d23631662-r945601429-Reviews-The_First_Collection_at_Jumeirah_Village_Circle-Dubai_Emirate_of_Dubai.html?m=66827#review945601429",
      "text": "Bedroom was really nice, super comfy bed, BF was great and stuff was lovely. Rubel at reception and everyone at the pool bar and taxi service were amazing and very helpful. Pool area is really cool with big screen to watch sports. The small coffee place at reception has amazing cakes!",
      "title": "Great stay",
      "trip_type": "Friends getaway",
      "travel_date": "2024-04-30",
      "user": {
        "username": "Irelacu",
        "user_location": {
          "id": "187514",
          "name": "Madrid"
        },
        "avatar": {
          "thumbnail": "https://media-cdn.tripadvisor.com/media/photo-t/0b/72/76/70/irelacu.jpg",
          "small": "https://media-cdn.tripadvisor.com/media/photo-l/0b/72/76/70/irelacu.jpg",
          "medium": "https://media-cdn.tripadvisor.com/media/photo-f/0b/72/76/70/irelacu.jpg",
          "large": "https://media-cdn.tripadvisor.com/media/photo-s/0b/72/76/70/irelacu.jpg"
        }
      },
      "subratings": {
        "0": {
          "name": "RATE_VALUE",
          "rating_image_url": "https://www.tripadvisor.com/img/cdsi/img2/ratings/traveler/s5.0-66827-5.svg",
          "value": 5,
          "localized_name": "Value"
        },
        "1": {
          "name": "RATE_ROOM",
          "rating_image_url": "https://www.tripadvisor.com/img/cdsi/img2/ratings/traveler/s5.0-66827-5.svg",
          "value": 5,
          "localized_name": "Rooms"
        },
        "2": {
          "name": "RATE_LOCATION",
          "rating_image_url": "https://www.tripadvisor.com/img/cdsi/img2/ratings/traveler/s4.0-66827-5.svg",
          "value": 4,
          "localized_name": "Location"
        },
        "3": {
          "name": "RATE_CLEANLINESS",
          "rating_image_url": "https://www.tripadvisor.com/img/cdsi/img2/ratings/traveler/s5.0-66827-5.svg",
          "value": 5,
          "localized_name": "Cleanliness"
        },
        "4": {
          "name": "RATE_SERVICE",
          "rating_image_url": "https://www.tripadvisor.com/img/cdsi/img2/ratings/traveler/s5.0-66827-5.svg",
          "value": 5,
          "localized_name": "Service"
        },
        "5": {
          "name": "RATE_SLEEP",
          "rating_image_url": "https://www.tripadvisor.com/img/cdsi/img2/ratings/traveler/s5.0-66827-5.svg",
          "value": 5,
          "localized_name": "Sleep Quality"
        }
      },
      "owner_response": {
        "id": 945736515,
        "title": "Owner response",
        "text": "Irelacu,  thank you so much for your incredibly review.\n\nWe are delighted to hear that you had a wonderful time with us. I am glad that facilities continue to impress and that our service made you feel looked after. We strive to provide a unique and memorable experience for all of our guests and we are thrilled to hear that you appreciated our hospitality. I will be sure to pass along your kind words to Rubel, whom I know will be delighted.\n\nWe are proud to have made an impression and are looking forward to hosting you again.\n\nWarm Regards,\nGeorge Ghaly",
        "lang": "en",
        "author": "George Ghaly",
        "published_date": "2024-04-07T14:36:15Z"
      }
    }
  ]
}