{
  "location_id": "1139697",
  "name": "Holiday Inn Dubai - Al Barsha",
  "description": "A stylish, cosmopolitan hotel amid the buzzing streets of New Dubai.\n\nIn the heart of the city, at the center of the world's tallest skyline, the Holiday Inn® Dubai - Al Barsha offers custom-designed accommodation next to Mall of the Emirates and near to Burj Khalifa, Dubai Sports City and Emirates Golf Course. For holidaymakers and families, the hotel makes a perfect base for sightseeing in Dubai. You can shop at state-of-the-art malls, explore centuries-old markets and souks. Business travelers will find meeting and conference facilities for up to 300 people and a Business Center. Sheikh Zayed Road puts you close to Dubai Internet City and Dubai Media City, and just a 15-minute drive from the World Trade Center. Dubai Airport is a 20-minute drive, Abu Dhabi Airport is 45 minutes and Dubai World Central Al Maktoum Airport is 35 minutes.",
  "web_url": "https://www.tripadvisor.com/Hotel_Review-g295424-d1139697-Reviews-Holiday_Inn_Dubai_Al_Barsha-Dubai_Emirate_of_Dubai.html?m=66827",
  "address_obj": {
    "street1": "Al Barsha 1, Sheikh Zayed Road",
    "street2": "Sheikh Zayed Road, Next To Mall of the, Emirates And Mashreq Metro Station",
    "city": "Dubai",
    "state": "Emirate of Dubai",
    "country": "United Arab Emirates",
    "postalcode": "115443",
    "address_string": "Al Barsha 1, Sheikh Zayed Road Sheikh Zayed Road, Next To Mall of the, Emirates And Mashreq Metro Station, Dubai 115443 United Arab Emirates"
  },
  "ancestors": [
    {
      "level": "Municipality",
      "name": "Dubai",
      "location_id": "295424"
    },
    {
      "level": "Province",
      "name": "Emirate of Dubai",
      "location_id": "2630221"
    },
    {
      "level": "Country",
      "name": "United Arab Emirates",
      "location_id": "294012"
    }
  ],
  "latitude": "25.116335",
  "longitude": "55.193726",
  "timezone": "Asia/Dubai",
  "phone": "18778595095",
  "write_review": "https://www.tripadvisor.com/UserReview-g295424-d1139697-Holiday_Inn_Dubai_Al_Barsha-Dubai_Emirate_of_Dubai.html?m=66827",
  "ranking_data": {
    "geo_location_id": "295424",
    "ranking_string": "#310 of 982 hotels in Dubai",
    "geo_location_name": "Dubai",
    "ranking_out_of": "982",
    "ranking": "310"
  },
  "rating": "4.5",
  "rating_image_url": "https://www.tripadvisor.com/img/cdsi/img2/ratings/traveler/4.5-66827-5.svg",
  "num_reviews": "1775",
  "review_rating_count": {
    "1": "39",
    "2": "41",
    "3": "173",
    "4": "646",
    "5": "876"
  },
  "subratings": {
    "0": {
      "name": "rate_location",
      "localized_name": "Location",
      "rating_image_url": "https://static.tacdn.com/img2/ratings/traveler/ss4.5.svg",
      "value": "4.5"
    },
    "1": {
      "name": "rate_sleep",
      "localized_name": "Sleep Quality",
      "rating_image_url": "https://static.tacdn.com/img2/ratings/traveler/ss4.5.svg",
      "value": "4.5"
    },
    "2": {
      "name": "rate_room",
      "localized_name": "Rooms",
      "rating_image_url": "https://static.tacdn.com/img2/ratings/traveler/ss4.0.svg",
      "value": "4.0"
    },
    "3": {
      "name": "rate_service",
      "localized_name": "Service",
      "rating_image_url": "https://static.tacdn.com/img2/ratings/traveler/ss4.5.svg",
      "value": "4.5"
    },
    "4": {
      "name": "rate_value",
      "localized_name": "Value",
      "rating_image_url": "https://static.tacdn.com/img2/ratings/traveler/ss4.0.svg",
      "value": "4.0"
    },
    "5": {
      "name": "rate_cleanliness",
      "localized_name": "Cleanliness",
      "rating_image_url": "https://static.tacdn.com/img2/ratings/traveler/ss4.5.svg",
      "value": "4.5"
    }
  },
  "photo_count": "1335",
  "see_all_photos": "https://www.tripadvisor.com/Hotel_Review-g295424-d1139697-m66827-Reviews-Holiday_Inn_Dubai_Al_Barsha-Dubai_Emirate_of_Dubai.html#photos",
  "price_level": "$$",
  "hours": {
    "periods": [
      {
        "open": {
          "day": 1,
          "time": "0000"
        },
        "close": {
          "day": 1,
          "time": "0000"
        }
      },
      {
        "open": {
          "day": 2,
          "time": "0000"
        },
        "close": {
          "day": 2,
          "time": "0000"
        }
      },
      {
        "open": {
          "day": 3,
          "time": "0000"
        },
        "close": {
          "day": 3,
          "time": "0000"
        }
      },
      {
        "open": {
          "day": 4,
          "time": "0000"
        },
        "close": {
          "day": 4,
          "time": "0000"
        }
      },
      {
        "open": {
          "day": 5,
          "time": "0000"
        },
        "close": {
          "day": 5,
          "time": "0000"
        }
      },
      {
        "open": {
          "day": 6,
          "time": "0000"
        },
        "close": {
          "day": 6,
          "time": "0000"
        }
      },
      {
        "open": {
          "day": 7,
          "time": "0000"
        },
        "close": {
          "day": 7,
          "time": "0000"
        }
      }
    ],
    "weekday_text": [
      "Monday: 00:00 - 00:00",
      "Tuesday: 00:00 - 00:00",
      "Wednesday: 00:00 - 00:00",
      "Thursday: 00:00 - 00:00",
      "Friday: 00:00 - 00:00",
      "Saturday: 00:00 - 00:00",
      "Sunday: 00:00 - 00:00"
    ]
  },
  "amenities": [
    "Pool",
    "Business center",
    "Room service",
    "Free parking",
    "Restaurant",
    "Fitness center",
    "Wheelchair access",
    "Bar/Lounge",
    "Meeting rooms",
    "Internet",
    "Free Internet",
    "Spa",
    "Wifi",
    "Free Wifi",
    "Laundry Service",
    "Concierge",
    "Suites",
    "Airport transportation",
    "Public Wifi",
    "Breakfast included",
    "Dry Cleaning",
    "Non-smoking rooms",
    "Banquet Room",
    "Air conditioning",
    "Family Rooms",
    "Multilingual Staff",
    "Minibar",
    "Conference Facilities",
    "Safe",
    "Rooftop Bar",
    "Rooftop Pool",
    "Heated pool",
    "Flatscreen TV",
    "Rooftop Terrace",
    "Breakfast Buffet",
    "Poolside Bar",
    "Outdoor pool",
    "Parking",
    "Facilities for Disabled Guests",
    "Housekeeping",
    "Kids Stay Free",
    "Sauna",
    "Arabic",
    "Baggage Storage",
    "Blackout Curtains",
    "Breakfast in the Room",
    "Car Hire",
    "24-Hour Check-in",
    "Coffee / Tea Maker",
    "Doorperson",
    "English",
    "Filipino",
    "Fitness / Spa Locker Rooms",
    "Complimentary Instant Cofffee",
    "24-Hour Front Desk",
    "Hair Dryer",
    "Hindi",
    "Interconnected room(s) available",
    "Ironing Service",
    "Kid-Friendly Buffet",
    "Nightclub / DJ",
    "Salon",
    "24-Hour Security",
    "Steam Room",
    "Taxi Service",
    "VIP Room Facilities",
    "Breakfast Available",
    "Chinese",
    "French",
    "Spanish",
    "Thai"
  ],
  "parent_brand": "InterContinental",
  "brand": "Holiday Inn",
  "category": {
    "name": "hotel",
    "localized_name": "Hotel"
  },
  "subcategory": [
    {
      "name": "hotel",
      "localized_name": "Hotel"
    }
  ],
  "styles": [
    "Mid-range",
    "Quiet"
  ],
  "neighborhood_info": [
    {
      "location_id": "15620543",
      "name": "Al Barsha"
    },
    {
      "location_id": "15620544",
      "name": "Al Barsha 1"
    }
  ],
  "trip_types": [
    {
      "name": "business",
      "localized_name": "Business",
      "value": "615"
    },
    {
      "name": "couples",
      "localized_name": "Couples",
      "value": "382"
    },
    {
      "name": "solo",
      "localized_name": "Solo travel",
      "value": "149"
    },
    {
      "name": "family",
      "localized_name": "Family",
      "value": "326"
    },
    {
      "name": "friends",
      "localized_name": "Friends getaway",
      "value": "185"
    }
  ],
  "awards": [
    {
      "award_type": "Travelers Choice",
      "year": "2023",
      "images": {
        "tiny": "https://static.tacdn.com/img2/travelers_choice/widgets/tchotel_2023_L.png",
        "small": "https://static.tacdn.com/img2/travelers_choice/widgets/tchotel_2023_L.png",
        "large": "https://static.tacdn.com/img2/travelers_choice/widgets/tchotel_2023_L.png"
      },
      "categories": [],
      "display_name": "Travelers Choice"
    },
    {
      "award_type": "Travelers Choice",
      "year": "2022",
      "images": {
        "tiny": "https://static.tacdn.com/img2/travelers_choice/widgets/tchotel_2022_L.png",
        "small": "https://static.tacdn.com/img2/travelers_choice/widgets/tchotel_2022_L.png",
        "large": "https://static.tacdn.com/img2/travelers_choice/widgets/tchotel_2022_L.png"
      },
      "categories": [],
      "display_name": "Travelers Choice"
    }
  ]
}